<?xml version='1.0' encoding='utf-8'?>
<carrier_config_list>
    <carrier_config>
        <!-- 2020-06-23 DCM SIM IMS Configuration [START] -->
        <boolean name="carrier_volte_available_bool" value="true" />
        <boolean name="carrier_vt_available_bool" value="true"/>
        <boolean name="vilte_data_is_metered_bool" value="false"/>
        <boolean name="carrier_rcs_provisioning_required_bool" value="false"/>
        <boolean name="carrier_volte_tty_supported_bool" value="false" />
        <boolean name="support_ims_conference_call_bool" value="false"/>
        <boolean name="local_disconnect_empty_ims_conference_bool" value="true"/>
        <boolean name="allow_hold_call_during_emergency_bool" value="false"/>
        <boolean name="allow_add_call_during_video_call" value="false"/>
        <boolean name="allow_hold_video_call_bool" value="false"/>
        <boolean name="tty_supported_bool" value="false"/>
        <boolean name="support_wps_over_ims_bool" value="false"/>
        <boolean name="carrier_use_ims_first_for_emergency_bool" value="false"/>
        <!-- 2020-06-23 DCM SIM IMS Configuration [END] -->
    </carrier_config>
    <carrier_config mnc="51">
        <!-- 2020-06-23 KDDI SIM IMS Configuration [START] -->
        <boolean name="carrier_vt_available_bool" value="false"/>
        <boolean name="vilte_data_is_metered_bool" value="true"/>
        <boolean name="carrier_supports_ss_over_ut_bool" value="true"/>
        <boolean name="carrier_allow_turnoff_ims_bool" value="false"/>
        <boolean name="carrier_ims_gba_required_bool" value="false"/>
        <boolean name="support_ims_conference_event_package_bool" value="false"/>
        <boolean name="support_ims_conference_event_package_on_peer_bool" value="false"/>
        <boolean name="support_ims_conference_call_bool" value="true"/>
        <boolean name="allow_add_call_during_video_call" value="true"/>
        <boolean name="allow_hold_video_call_bool" value="true"/>
        <!-- 2020-06-23 KDDI SIM IMS Configuration [END] -->
    </carrier_config>
    <carrier_config mnc="20">
        <!-- 2020-06-23 SB SIM IMS Configuration [START] -->
        <boolean name="carrier_vt_available_bool" value="false"/>
        <boolean name="vilte_data_is_metered_bool" value="true"/>
        <boolean name="carrier_supports_ss_over_ut_bool" value="true"/>
        <boolean name="carrier_ims_gba_required_bool" value="false"/>
        <boolean name="support_ims_conference_call_bool" value="true"/>
        <boolean name="allow_add_call_during_video_call" value="true"/>
        <boolean name="allow_hold_video_call_bool" value="true"/>
        <!-- 2020-06-23 SB SIM IMS Configuration [END] -->
    </carrier_config>
</carrier_config_list>
